forgetting_machine/__init__.py
forgetting_machine-0.0.1.dist-info/licenses/LICENSE
forgetting_machine-0.0.1.dist-info/METADATA
forgetting_machine-0.0.1.dist-info/WHEEL
forgetting_machine-0.0.1.dist-info/top_level.txt
forgetting_machine-0.0.1.dist-info/RECORD
