Metadata-Version: 2.4
Name: forgetting-machine
Version: 0.0.1
Summary: A Machine that forgets what had been memorized.
Author-email: Alexander Fedotov <alex.fedotov@aol.com>
Project-URL: Homepage, https://github.com/forgetting-machine/forgetting-machine
Project-URL: Bug Tracker, https://github.com/forgetting-machine/forgetting-machine/issues
Classifier: Programming Language :: Python :: 3
Classifier: License :: OSI Approved :: MIT License
Classifier: Operating System :: OS Independent
Requires-Python: >=3.10
License-File: LICENSE
Dynamic: license-file
